{"chunk_definitions":[{"row":35,"row_count":1,"visible":true,"expansion_state":0,"options":{"engine":"r","label":"unnamed-chunk-1","dev":"png"},"document_id":"3FE0AA0E","chunk_id":"ci9fpx43vxkso","chunk_label":"unnamed-chunk-1"},{"row":47,"row_count":1,"visible":true,"expansion_state":0,"options":{"engine":"r","label":"unnamed-chunk-2","dev":"png"},"document_id":"AF184D01","chunk_id":"cx5nk5ikqx8de","chunk_label":"unnamed-chunk-2"},{"row":57,"row_count":1,"visible":true,"expansion_state":0,"options":{"engine":"r","label":"unnamed-chunk-3","dev":"png"},"document_id":"3FE0AA0E","chunk_id":"ce303irx8wkpn","chunk_label":"unnamed-chunk-3"},{"row":65,"row_count":1,"visible":true,"expansion_state":0,"options":{"engine":"r","label":"unnamed-chunk-4","dev":"png"},"document_id":"3FE0AA0E","chunk_id":"cvq3xc7wead4f","chunk_label":"unnamed-chunk-4"},{"row":72,"row_count":1,"visible":true,"expansion_state":0,"options":{"engine":"r","label":"unnamed-chunk-5","dev":"png"},"document_id":"3FE0AA0E","chunk_id":"c55q0yg571gml","chunk_label":"unnamed-chunk-5"},{"row":179,"row_count":1,"visible":true,"expansion_state":0,"options":{"engine":"r","label":"unnamed-chunk-6","dev":"png"},"document_id":"AF184D01","chunk_id":"cbicyfcrs2jof","chunk_label":"unnamed-chunk-6"},{"row":203,"row_count":1,"visible":true,"expansion_state":0,"options":{"engine":"r","label":"unnamed-chunk-7","dev":"png"},"document_id":"3FE0AA0E","chunk_id":"c5c61qa177hw4","chunk_label":"unnamed-chunk-8"},{"row":230,"row_count":1,"visible":true,"expansion_state":0,"options":{"engine":"r","label":"unnamed-chunk-8","dev":"png"},"document_id":"AF184D01","chunk_id":"cig0bxnb85pvt","chunk_label":"unnamed-chunk-9"},{"row":290,"row_count":1,"visible":true,"expansion_state":0,"options":{"engine":"r","label":"unnamed-chunk-9","results":"hide","message":false,"dev":"png"},"document_id":"3FE0AA0E","chunk_id":"cgyct5o2j4lno","chunk_label":"unnamed-chunk-12"},{"row":299,"row_count":1,"visible":true,"expansion_state":0,"options":{"engine":"r","label":"unnamed-chunk-10","eval":false,"dev":"png"},"document_id":"AF184D01","chunk_id":"cr160uyw0gvoo","chunk_label":"unnamed-chunk-13"},{"row":316,"row_count":1,"visible":true,"expansion_state":0,"options":{"engine":"r","label":"unnamed-chunk-10","dev":"png"},"document_id":"3FE0AA0E","chunk_id":"cap29zlwn9o4p","chunk_label":"unnamed-chunk-14"},{"row":322,"row_count":1,"visible":true,"expansion_state":0,"options":{"engine":"r","label":"unnamed-chunk-11","dev":"png"},"document_id":"AF184D01","chunk_id":"crpsuu5xk73i1","chunk_label":"unnamed-chunk-15"},{"row":344,"row_count":1,"visible":true,"expansion_state":0,"options":{"engine":"r","label":"unnamed-chunk-12","results":"hide","dev":"png"},"document_id":"AF184D01","chunk_id":"cfv4ubmyw8flg","chunk_label":"unnamed-chunk-16"},{"row":361,"row_count":1,"visible":true,"expansion_state":0,"options":{"engine":"r","label":"unnamed-chunk-13","results":"hide","dev":"png"},"document_id":"AF184D01","chunk_id":"c9vl9l10k1gaf","chunk_label":"unnamed-chunk-17"},{"row":393,"row_count":1,"visible":true,"expansion_state":0,"options":{"engine":"r","label":"unnamed-chunk-14","dev":"png"},"document_id":"AF184D01","chunk_id":"cqlr853fisonz","chunk_label":"unnamed-chunk-18"},{"row":454,"row_count":1,"visible":true,"expansion_state":0,"options":{"engine":"r","label":"unnamed-chunk-15","dev":"png"},"document_id":"3FE0AA0E","chunk_id":"czz9tnlo1z92r","chunk_label":"unnamed-chunk-19"},{"row":463,"row_count":1,"visible":true,"expansion_state":0,"options":{"engine":"r","label":"unnamed-chunk-16","echo":false,"dev":"png"},"document_id":"AF184D01","chunk_id":"c25qqz8o39igl","chunk_label":"unnamed-chunk-20"},{"row":502,"row_count":1,"visible":true,"expansion_state":0,"options":{"engine":"r","label":"unnamed-chunk-17","dev":"png"},"document_id":"AF184D01","chunk_id":"cd53lbf1u5610","chunk_label":"unnamed-chunk-21"},{"row":193,"row_count":1,"visible":true,"expansion_state":0,"options":{"engine":"r","label":"unnamed-chunk-10","dev":"png"},"document_id":"AF184D01","chunk_id":"ccmbovydt1fei","chunk_label":"unnamed-chunk-7"}],"doc_write_time":1776430225}